vllm_inference/__init__.py
vllm_inference/inference.py
vllm_inference/model.py
vllm_inference/translation/__init__.py
vllm_inference/translation/seed_x.py
vllm_inference-0.0.19.dist-info/METADATA
vllm_inference-0.0.19.dist-info/WHEEL
vllm_inference-0.0.19.dist-info/top_level.txt
vllm_inference-0.0.19.dist-info/RECORD
