Metadata-Version: 2.4
Name: vllm-inference
Version: 0.0.19
Summary: Inference locally.
Requires-Python: >=3.10
Requires-Dist: fastapi>=0.116.1
Requires-Dist: transformers==4.51.3
Requires-Dist: uvicorn>=0.35.0
Requires-Dist: vllm>=0.8.5.post1
Requires-Dist: vortezwohl>=0.0.8
